{
	"info": {
		"_postman_id": "63db12f2-3e39-4409-ac4f-99244e72d4c6",
		"name": "mx-master-2",
		"schema": "https://schema.getpostman.com/json/collection/v2.1.0/collection.json"
	},
	"item": [
		{
			"name": "limits-service-1 8080 config-server",
			"request": {
				"method": "GET",
				"header": [],
				"url": {
					"raw": "http://localhost:8080/limits",
					"protocol": "http",
					"host": [
						"localhost"
					],
					"port": "8080",
					"path": [
						"limits"
					]
				}
			},
			"response": []
		},
		{
			"name": "config-server default profile",
			"request": {
				"method": "GET",
				"header": [],
				"url": {
					"raw": "http://localhost:8888/limits-service/default",
					"protocol": "http",
					"host": [
						"localhost"
					],
					"port": "8888",
					"path": [
						"limits-service",
						"default"
					]
				}
			},
			"response": []
		},
		{
			"name": "config-server dev profile",
			"request": {
				"method": "GET",
				"header": [],
				"url": {
					"raw": "http://localhost:8888/limits-service/dev",
					"protocol": "http",
					"host": [
						"localhost"
					],
					"port": "8888",
					"path": [
						"limits-service",
						"dev"
					]
				}
			},
			"response": []
		},
		{
			"name": "config-server qa profile",
			"request": {
				"method": "GET",
				"header": [],
				"url": {
					"raw": "http://localhost:8888/limits-service/qa",
					"protocol": "http",
					"host": [
						"localhost"
					],
					"port": "8888",
					"path": [
						"limits-service",
						"qa"
					]
				}
			},
			"response": []
		},
		{
			"name": "currency-exchange 8000",
			"request": {
				"method": "GET",
				"header": [],
				"url": {
					"raw": "http://localhost:8000/currency-exchange/from/USD/to/INR",
					"protocol": "http",
					"host": [
						"localhost"
					],
					"port": "8000",
					"path": [
						"currency-exchange",
						"from",
						"USD",
						"to",
						"INR"
					]
				}
			},
			"response": []
		},
		{
			"name": "currency-exchange 8001",
			"request": {
				"method": "GET",
				"header": [],
				"url": {
					"raw": "http://localhost:8001/currency-exchange/from/USD/to/INR",
					"protocol": "http",
					"host": [
						"localhost"
					],
					"port": "8001",
					"path": [
						"currency-exchange",
						"from",
						"USD",
						"to",
						"INR"
					]
				}
			},
			"response": []
		},
		{
			"name": "currency-converter 8100",
			"request": {
				"method": "GET",
				"header": [],
				"url": {
					"raw": "http://localhost:8100/currency-converter/from/USD/to/INR/quantity/1000",
					"protocol": "http",
					"host": [
						"localhost"
					],
					"port": "8100",
					"path": [
						"currency-converter",
						"from",
						"USD",
						"to",
						"INR",
						"quantity",
						"1000"
					]
				}
			},
			"response": []
		},
		{
			"name": "currency-converter 8100 feign + ribbon",
			"request": {
				"method": "GET",
				"header": [],
				"url": {
					"raw": "http://localhost:8100/currency-converter/from/USD/to/INR/quantity/1000",
					"protocol": "http",
					"host": [
						"localhost"
					],
					"port": "8100",
					"path": [
						"currency-converter",
						"from",
						"USD",
						"to",
						"INR",
						"quantity",
						"1000"
					]
				}
			},
			"response": []
		},
		{
			"name": "currency-converter 8100 feign + ribbon + eureka",
			"request": {
				"method": "GET",
				"header": [],
				"url": {
					"raw": "http://localhost:8100/currency-converter/from/USD/to/INR/quantity/1000",
					"protocol": "http",
					"host": [
						"localhost"
					],
					"port": "8100",
					"path": [
						"currency-converter",
						"from",
						"USD",
						"to",
						"INR",
						"quantity",
						"1000"
					]
				}
			},
			"response": []
		},
		{
			"name": "currency-exchange zuul 8765",
			"request": {
				"method": "GET",
				"header": [],
				"url": {
					"raw": "http://localhost:8765/currency-exchange-service/currency-exchange/from/USD/to/INR",
					"protocol": "http",
					"host": [
						"localhost"
					],
					"port": "8765",
					"path": [
						"currency-exchange-service",
						"currency-exchange",
						"from",
						"USD",
						"to",
						"INR"
					]
				}
			},
			"response": []
		},
		{
			"name": "currency-converter 8100 feign+ribbon+eureka+proxy-zuul",
			"request": {
				"method": "GET",
				"header": [],
				"url": {
					"raw": "http://localhost:8100/currency-converter/from/USD/to/INR/quantity/1000",
					"protocol": "http",
					"host": [
						"localhost"
					],
					"port": "8100",
					"path": [
						"currency-converter",
						"from",
						"USD",
						"to",
						"INR",
						"quantity",
						"1000"
					]
				}
			},
			"response": []
		},
		{
			"name": "currency-converter 8765 zuul feign+ribbon+eureka",
			"request": {
				"method": "GET",
				"header": [],
				"url": {
					"raw": "http://localhost:8765/currency-exchange-service/currency-exchange/from/USD/to/INR",
					"protocol": "http",
					"host": [
						"localhost"
					],
					"port": "8765",
					"path": [
						"currency-exchange-service",
						"currency-exchange",
						"from",
						"USD",
						"to",
						"INR"
					]
				}
			},
			"response": []
		},
		{
			"name": "limits-service-1 8081 config-server",
			"request": {
				"method": "GET",
				"header": [],
				"url": {
					"raw": "http://localhost:8081/limits",
					"protocol": "http",
					"host": [
						"localhost"
					],
					"port": "8081",
					"path": [
						"limits"
					]
				}
			},
			"response": []
		},
		{
			"name": "limits-service-1 8080 config-server refresh",
			"request": {
				"method": "POST",
				"header": [],
				"url": {
					"raw": "http://localhost:8080/actuator/refresh",
					"protocol": "http",
					"host": [
						"localhost"
					],
					"port": "8080",
					"path": [
						"actuator",
						"refresh"
					]
				}
			},
			"response": []
		},
		{
			"name": "limits-service-1 8081 config-server refresh",
			"request": {
				"method": "POST",
				"header": [],
				"url": {
					"raw": "http://localhost:8081/actuator/refresh",
					"protocol": "http",
					"host": [
						"localhost"
					],
					"port": "8081",
					"path": [
						"actuator",
						"refresh"
					]
				}
			},
			"response": []
		},
		{
			"name": "limits-service-1 8080 bus refresh",
			"request": {
				"method": "POST",
				"header": [],
				"url": {
					"raw": "http://localhost:8080/actuator/bus-refresh",
					"protocol": "http",
					"host": [
						"localhost"
					],
					"port": "8080",
					"path": [
						"actuator",
						"bus-refresh"
					]
				}
			},
			"response": []
		},
		{
			"name": "limits-service-1 8080 config-server hystrix",
			"request": {
				"method": "GET",
				"header": [],
				"url": {
					"raw": "http://localhost:8080//fault-tolerance-example",
					"protocol": "http",
					"host": [
						"localhost"
					],
					"port": "8080",
					"path": [
						"",
						"fault-tolerance-example"
					]
				}
			},
			"response": []
		}
	],
	"protocolProfileBehavior": {}
}